streamlit_achievements/__init__.py
streamlit_achievements/frontend/index.html
streamlit_achievements/frontend/main.js
streamlit_achievements/frontend/streamlit-component-lib.js
streamlit_achievements/frontend/style.css
streamlit_achievements-0.1.1.dist-info/licenses/LICENSE
streamlit_achievements-0.1.1.dist-info/METADATA
streamlit_achievements-0.1.1.dist-info/WHEEL
streamlit_achievements-0.1.1.dist-info/top_level.txt
streamlit_achievements-0.1.1.dist-info/RECORD
