Metadata-Version: 2.4
Name: streamlit-achievements
Version: 0.1.1
Summary: Streamlit component that lets you have achievements in your application
Author: lejuliennn
Author-email: julien.playsde@gmail.com
Requires-Python: >=3.7
License-File: LICENSE
Requires-Dist: streamlit>=1.2
Requires-Dist: jinja2
Dynamic: author
Dynamic: author-email
Dynamic: description
Dynamic: description-content-type
Dynamic: license-file
Dynamic: requires-dist
Dynamic: requires-python
Dynamic: summary
